hafsqlpublish/__init__.py
hafsqlpublish/createhaf.py
hafsqlpublish/db_api.py
hafsqlpublish/db_app.py
hafsqlpublish/db_common.py
hafsqlpublish/db_web.py
hafsqlpublish/publish.py
hafsqlpublish-0.0.8.dist-info/LICENSE
hafsqlpublish-0.0.8.dist-info/METADATA
hafsqlpublish-0.0.8.dist-info/WHEEL
hafsqlpublish-0.0.8.dist-info/entry_points.txt
hafsqlpublish-0.0.8.dist-info/top_level.txt
hafsqlpublish-0.0.8.dist-info/RECORD
