Metadata-Version: 2.1
Name: hafsqlpublish
Version: 0.0.8
Summary: UNKNOWN
Home-page: http://github.com/hautof/haf-plugin-webserver
Author: wei.meng
Author-email: mengwei1101@hotmail.com
License: UNKNOWN
Platform: Posix; MacOS X; Windows
Classifier: Development Status :: 5 - Production/Stable
Classifier: Intended Audience :: Developers
Classifier: License :: OSI Approved :: MIT License
Classifier: Operating System :: OS Independent
Classifier: Topic :: Software Development :: Libraries
Classifier: Topic :: Software Development :: Libraries :: Python Modules
Classifier: Topic :: Software Development :: Testing
Classifier: Programming Language :: Python
Classifier: Programming Language :: Python :: 3.6
Classifier: Programming Language :: Python :: 3.7
Requires-Python: >=3.6
Requires-Dist: haf
Requires-Dist: twine
Requires-Dist: setuptools
